MANIFEST.in
README.md
setup.py
MLMath.egg-info/PKG-INFO
MLMath.egg-info/SOURCES.txt
MLMath.egg-info/dependency_links.txt
MLMath.egg-info/requires.txt
MLMath.egg-info/top_level.txt
mlm/VERSION
mlm/__init__.py
mlm/_troubleshoot.py
mlm/jax/__init__.py
mlm/jax/_jax_backend.py
mlm/jax/flow.py
mlm/jax/stax/__init__.py
mlm/jax/stax/flow.py
mlm/jax/stax/nets.py
mlm/math/__init__.py
mlm/math/_fit.py
mlm/math/_functional.py
mlm/math/_magic_ops.py
mlm/math/_nd.py
mlm/math/_ops.py
mlm/math/_shape.py
mlm/math/_tensors.py
mlm/math/extrapolation.py
mlm/math/magic.py
mlm/math/backend/__init__.py
mlm/math/backend/_backend.py
mlm/math/backend/_dtype.py
mlm/math/backend/_numpy_backend.py
mlm/math/backend/_profile.py
mlm/tf/__init__.py
mlm/tf/_compile_cuda.py
mlm/tf/_profiling.py
mlm/tf/_tf_backend.py
mlm/tf/_tf_cuda_resample.py
mlm/tf/flow.py
mlm/tf/nets.py
mlm/torch/__init__.py
mlm/torch/_torch_backend.py
mlm/torch/flow.py
mlm/torch/nets.py