Metadata-Version: 2.1
Name: MLMath
Version: 0.0.0rc1
Summary: Differentiable PDE solving framework for machine learning
Home-page: https://github.com/tum-pbs/MLM
Author: Philipp Holl
Author-email: philipp.holl@tum.de
License: MIT
Download-URL: https://github.com/tum-pbs/MLM/archive/0.0.0-rc1.tar.gz
Keywords: Differentiable,Simulation,Fluid,Machine Learning,Deep Learning
Platform: UNKNOWN
Classifier: Development Status :: 5 - Production/Stable
Classifier: Intended Audience :: Developers
Classifier: Topic :: Software Development :: Build Tools
Classifier: License :: OSI Approved :: MIT License
Classifier: Programming Language :: Python :: 3
Classifier: Programming Language :: Python :: 3.6
Classifier: Programming Language :: Python :: 3.7
Classifier: Programming Language :: Python :: 3.8
Classifier: Programming Language :: Python :: 3.9
Classifier: Programming Language :: Python :: 3.10
